loudds/__init__.py
loudds/fastai/__init__.py
loudds/fastai/fastai.py
loudds/pytorch/__init__.py
loudds/pytorch/pytorch.py
loudds-0.0.6.dist-info/DESCRIPTION.rst
loudds-0.0.6.dist-info/METADATA
loudds-0.0.6.dist-info/RECORD
loudds-0.0.6.dist-info/WHEEL
loudds-0.0.6.dist-info/metadata.json
loudds-0.0.6.dist-info/top_level.txt
